azqueuemanager_json/__init__.py
azqueuemanager_json/tests/test.py
azqueuemanager_json-0.0.2.dist-info/LICENSE
azqueuemanager_json-0.0.2.dist-info/METADATA
azqueuemanager_json-0.0.2.dist-info/WHEEL
azqueuemanager_json-0.0.2.dist-info/top_level.txt
azqueuemanager_json-0.0.2.dist-info/RECORD
