Metadata-Version: 2.1
Name: azqueuemanager-json
Version: 0.0.2
Summary: JSON for AZQueueManager
License: MIT
Keywords: azqueuemanager,extension,json
Classifier: Programming Language :: Python :: 3
Requires-Python: >=3.10
License-File: LICENSE
Requires-Dist: azqueuemanager
